xy_django_app_api_auth/__init__.py
xy_django_app_api_auth/abstracts.py
xy_django_app_api_auth/admin.py
xy_django_app_api_auth/apps.py
xy_django_app_api_auth/models.py
xy_django_app_api_auth/serializers.py
xy_django_app_api_auth/tests.py
xy_django_app_api_auth/views.py
xy_django_app_api_auth/migrations/__init__.py
xy_django_app_api_auth-1.0.0.dist-info/LICENSE
xy_django_app_api_auth-1.0.0.dist-info/METADATA
xy_django_app_api_auth-1.0.0.dist-info/WHEEL
xy_django_app_api_auth-1.0.0.dist-info/top_level.txt
xy_django_app_api_auth-1.0.0.dist-info/RECORD
